dims_client/__init__.py
dims_client/client_registration.py
dims_client/data_registration.py
dims_client/service_registration.py
dims_client-0.0.4.dist-info/METADATA
dims_client-0.0.4.dist-info/WHEEL
dims_client-0.0.4.dist-info/top_level.txt
dims_client-0.0.4.dist-info/RECORD
