Metadata-Version: 2.1
Name: dims-client
Version: 0.0.4
Summary: Raspberry Pi Client Registration
Home-page: https://uiot.org/
Author: Jonathas
Author-email: jhsalves@gmail.com
License: UNKNOWN
Keywords: Universal Internet of Things Raspberry Client
Platform: UNKNOWN
Classifier: Intended Audience :: Information Technology
Classifier: Intended Audience :: Science/Research
Classifier: Natural Language :: English
Classifier: Operating System :: POSIX :: Linux
Classifier: Programming Language :: Python :: 3.7
Classifier: Topic :: Scientific/Engineering
Requires-Dist: requests
Requires-Dist: uuid
Requires-Dist: geocoder
Requires-Dist: argparse
